AUTHORS.txt
CHANGES.txt
LGPL2.1.txt
LICENSE.txt
MANIFEST.in
README.txt
distribute_setup.py
setup.cfg
setup.py
RTMPy.egg-info/PKG-INFO
RTMPy.egg-info/SOURCES.txt
RTMPy.egg-info/dependency_links.txt
RTMPy.egg-info/requires.txt
RTMPy.egg-info/top_level.txt
RTMPy.egg-info/zip-safe
doc/Makefile
doc/about.rst
doc/bugs.rst
doc/changelog.rst
doc/conf.py
doc/contents.rst
doc/install.rst
doc/license.rst
doc/make.bat
doc/architecture/index.rst
doc/architecture/overview.rst
doc/community/download.rst
doc/community/index.rst
doc/community/irc.rst
doc/community/mailinglist.rst
doc/community/maintainers.rst
doc/community/team.rst
doc/html/defindex.html
doc/html/intro.html
doc/html/layout.html
doc/html/tutorials.html
doc/html/static/logo.png
doc/tutorials/index.rst
doc/tutorials/examples/general/client/basic.py
doc/tutorials/examples/general/helloworld/Readme.txt
doc/tutorials/examples/general/helloworld/python/server.py
doc/tutorials/general/index.rst
doc/tutorials/general/helloworld/index.rst
doc/whatsnew/0.1.rst
doc/whatsnew/index.rst
rtmpy/__init__.py
rtmpy/client.py
rtmpy/dispatcher.py
rtmpy/exc.py
rtmpy/server.py
rtmpy/statuscodes.py
rtmpy/util.py
rtmpy/versions.py
rtmpy/protocol/__init__.py
rtmpy/protocol/handshake.py
rtmpy/protocol/version.py
rtmpy/protocol/rtmp/__init__.py
rtmpy/protocol/rtmp/codec.py
rtmpy/protocol/rtmp/handshake.py
rtmpy/protocol/rtmp/header.c
rtmpy/protocol/rtmp/header.py
rtmpy/protocol/rtmp/message.py
rtmpy/protocol/rtmp/status.py
rtmpy/scripts/__init__.py
rtmpy/scripts/parse_dump.py
rtmpy/tests/rtmp/__init__.py
rtmpy/tests/rtmp/test_decoder.py
rtmpy/tests/rtmp/test_encoder.py
rtmpy/tests/rtmp/test_handshake.py
rtmpy/tests/rtmp/test_header.py
rtmpy/tests/rtmp/test_message.py
rtmpy/tests/rtmp/test_protocol.py