Metadata-Version: 1.0
Name: RTMPy
Version: 0.1.1
Summary: Twisted protocol for RTMP
Home-page: http://rtmpy.org
Author: The RTMPy Project
Author-email: rtmpy-dev@rtmpy.org
License: LGPL 2.1 License
Keywords: rtmp flv rtmps rtmpe rtmpt rtmpte amf amf0 amf3 flex flash http https
Platform: any
Classifier: Development Status :: 2 - Pre-Alpha
Classifier: Framework :: Twisted
Classifier: Natural Language :: English
Classifier: Intended Audience :: Developers
Classifier: Intended Audience :: Information Technology
Classifier: License :: OSI Approved :: GNU Library or Lesser General Public License (LGPL)
Classifier: Operating System :: OS Independent
Classifier: Programming Language :: Python
Classifier: Programming Language :: Python :: 2.4
Classifier: Programming Language :: Python :: 2.5
Classifier: Programming Language :: Python :: 2.6
Classifier: Programming Language :: Python :: 2.7
Classifier: Topic :: Software Development :: Libraries :: Python Modules
